binreader.py
binreader-1.1.dist-info/LICENSE
binreader-1.1.dist-info/METADATA
binreader-1.1.dist-info/WHEEL
binreader-1.1.dist-info/top_level.txt
binreader-1.1.dist-info/RECORD
