Metadata-Version: 2.1
Name: binreader
Version: 1.1
Summary: Python BinaryReader class
Home-page: https://github.com/jleclanche/binreader
Author: Jerome Leclanche
Author-email: jerome@leclan.ch
License: UNKNOWN
Download-URL: https://github.com/jleclanche/binreader/archive/master.zip
Platform: UNKNOWN
Classifier: Development Status :: 5 - Production/Stable
Classifier: Intended Audience :: Developers
Classifier: License :: CC0 1.0 Universal (CC0 1.0) Public Domain Dedication
Classifier: Programming Language :: Python
Classifier: Programming Language :: Python :: 3
Classifier: Programming Language :: Python :: 3.6
Classifier: Programming Language :: Python :: 3.7
Classifier: Topic :: System
